sanki/__init__.py
sanki/metrics.py
sanki/model.py
sanki/preprocess.py
sanki-0.1.0.dist-info/METADATA
sanki-0.1.0.dist-info/WHEEL
sanki-0.1.0.dist-info/top_level.txt
sanki-0.1.0.dist-info/RECORD
