Metadata-Version: 2.4
Name: sanki
Version: 0.1.0
Summary: Custom AI training library by Sanki
Author: Sanki
Author-email: schoudhary112566@gmail.com
Keywords: machine learning,ai,sanki
Classifier: Programming Language :: Python :: 3
Classifier: License :: OSI Approved :: MIT License
Classifier: Operating System :: OS Independent
Requires-Python: >=3.6
Dynamic: author
Dynamic: author-email
Dynamic: classifier
Dynamic: description
Dynamic: description-content-type
Dynamic: keywords
Dynamic: requires-python
Dynamic: summary
